xrandr_extend/__init__.py
xrandr_extend/cmd.py
xrandr_extend/config.py
xrandr_extend/default.cfg
xrandr_extend/main.py
xrandr_extend-0.3.0.dist-info/LICENSE
xrandr_extend-0.3.0.dist-info/METADATA
xrandr_extend-0.3.0.dist-info/WHEEL
xrandr_extend-0.3.0.dist-info/entry_points.txt
xrandr_extend-0.3.0.dist-info/top_level.txt
xrandr_extend-0.3.0.dist-info/RECORD
